betatester/__init__.py
betatester/betatester_types.py
betatester/cli.py
betatester/execution.py
betatester/model.py
betatester/prompts.py
betatester/file/__init__.py
betatester/file/local.py
betatester-0.0.2.dist-info/METADATA
betatester-0.0.2.dist-info/WHEEL
betatester-0.0.2.dist-info/entry_points.txt
betatester-0.0.2.dist-info/licenses/LICENSE
betatester-0.0.2.dist-info/RECORD
