Metadata-Version: 2.3
Name: betatester
Version: 0.0.2
Summary: A package for automatically testing the UX / UI of a website.
Project-URL: Homepage, https://github.com/pateli18/betatester
Project-URL: Issues, https://github.com/pateli18/betatester/issues
Author: Ihsaan Patel
License-File: LICENSE
Classifier: License :: OSI Approved :: Apache Software License
Classifier: Operating System :: OS Independent
Classifier: Programming Language :: Python :: 3
Requires-Python: >=3.10
Requires-Dist: beautifulsoup4
Requires-Dist: httpx
Requires-Dist: lxml
Requires-Dist: playwright
Requires-Dist: pydantic
Provides-Extra: cli
Requires-Dist: typer; extra == 'cli'
Provides-Extra: local
Requires-Dist: aiofiles; extra == 'local'
